pythonp2p/__init__.py
pythonp2p/__main__.py
pythonp2p/crypto_funcs.py
pythonp2p/file_transfer.py
pythonp2p/node.py
pythonp2p/portforwardlib.py
pythonp2p-1.7.1.dist-info/LICENSE
pythonp2p-1.7.1.dist-info/METADATA
pythonp2p-1.7.1.dist-info/WHEEL
pythonp2p-1.7.1.dist-info/top_level.txt
pythonp2p-1.7.1.dist-info/RECORD
