Metadata-Version: 2.1
Name: pythonp2p
Version: 1.7.1
Summary: A peer to peer network able to transfer data and files
Home-page: https://github.com/GianisTsol/python-p2p
Author: GianisTsol
Author-email: giannisetsolakis@gmail.com
License: UNKNOWN
Project-URL: Bug Tracker, https://github.com/GianisTsol/python-p2p/issues
Platform: UNKNOWN
Classifier: Programming Language :: Python :: 3
Classifier: License :: OSI Approved :: GNU General Public License v3 (GPLv3)
Classifier: Operating System :: OS Independent
Requires-Python: >=3.8
License-File: LICENSE
